andi/__init__.py
andi/andi.py
andi/errors.py
andi/py.typed
andi/typeutils.py
andi-0.7.0.dist-info/LICENSE
andi-0.7.0.dist-info/METADATA
andi-0.7.0.dist-info/WHEEL
andi-0.7.0.dist-info/top_level.txt
andi-0.7.0.dist-info/RECORD
